emp_boot.py
emp_ide.py
emp_utils.py
emp_webrepl.py
emp_wifi.py
emp_1zlab-0.2.4.dist-info/METADATA
emp_1zlab-0.2.4.dist-info/WHEEL
emp_1zlab-0.2.4.dist-info/top_level.txt
emp_1zlab-0.2.4.dist-info/RECORD
