Metadata-Version: 2.1
Name: emp-1zlab
Version: 0.2.4
Summary: EMP(Easy MicroPython) is a upy module to make things Easy on MicroPython.
Home-page: http://emp.1zlab.com
Author: fuermohao@1zlab.com
Author-email: fuermohao@outlook.com
License: UNKNOWN
Platform: UNKNOWN
